cassandra_sigv4/__init__.py
cassandra_sigv4/auth.py
cassandra_sigv4-4.0.2.dist-info/LICENSE
cassandra_sigv4-4.0.2.dist-info/METADATA
cassandra_sigv4-4.0.2.dist-info/NOTICE
cassandra_sigv4-4.0.2.dist-info/WHEEL
cassandra_sigv4-4.0.2.dist-info/top_level.txt
cassandra_sigv4-4.0.2.dist-info/RECORD
