Metadata-Version: 2.1
Name: cassandra-sigv4
Version: 4.0.2
Summary: Implements a sigv4 authentication plugin for the open-source Datastax Python Driver for Apache Cassandra
Home-page: https://github.com/aws/aws-sigv4-auth-cassandra-python-driver-plugin/
Author: AWS
License: UNKNOWN
Project-URL: Bug Reports, https://github.com/aws/aws-sigv4-auth-cassandra-python-driver-plugin/issues
Project-URL: Source, https://github.com/aws/aws-sigv4-auth-cassandra-python-driver-plugin/
Keywords: cassandra,cql,aws,sigv4,authentication,auth
Platform: UNKNOWN
Classifier: Development Status :: 5 - Production/Stable
Classifier: Intended Audience :: Developers
Classifier: License :: OSI Approved :: Apache Software License
Classifier: Operating System :: OS Independent
Classifier: Programming Language :: Python
Classifier: Programming Language :: Python :: 2.7
Classifier: Programming Language :: Python :: 3.4
Classifier: Programming Language :: Python :: 3.5
Classifier: Programming Language :: Python :: 3.6
Classifier: Programming Language :: Python :: 3.7
Classifier: Programming Language :: Python :: 3.8
Classifier: Programming Language :: Python :: Implementation :: CPython
Classifier: Programming Language :: Python :: Implementation :: PyPy
Classifier: Topic :: Software Development :: Libraries :: Python Modules
Requires-Python: >=2.7, <4
